mcp_django/__init__.py
mcp_django/__main__.py
mcp_django/_typing.py
mcp_django/apps.py
mcp_django/cli.py
mcp_django/management/__init__.py
mcp_django/management/commands/__init__.py
mcp_django/management/commands/mcp.py
mcp_django/mgmt/__init__.py
mcp_django/mgmt/core.py
mcp_django/mgmt/server.py
mcp_django/packages/__init__.py
mcp_django/packages/client.py
mcp_django/packages/server.py
mcp_django/project/__init__.py
mcp_django/project/resources.py
mcp_django/project/routing.py
mcp_django/project/server.py
mcp_django/py.typed
mcp_django/server.py
mcp_django/shell/__init__.py
mcp_django/shell/core.py
mcp_django/shell/output.py
mcp_django/shell/server.py
mcp_django-0.13.0.dist-info/WHEEL
mcp_django-0.13.0.dist-info/METADATA
mcp_django-0.13.0.dist-info/RECORD
