Metadata-Version: 2.3
Name: mcp-django
Version: 0.13.0
Summary: A Model Context Protocol (MCP) server for Django integration with LLM assistants.
Author: Josh Thomas
Author-email: Josh Thomas <josh@joshthomas.dev>
License: MIT License
Classifier: Development Status :: 4 - Beta
Classifier: Framework :: Django
Classifier: Framework :: Django :: 4.2
Classifier: Framework :: Django :: 5.1
Classifier: Framework :: Django :: 5.2
Classifier: Framework :: Django :: 6.0
Classifier: License :: OSI Approved :: MIT License
Classifier: Operating System :: OS Independent
Classifier: Programming Language :: Python
Classifier: Programming Language :: Python :: 3
Classifier: Programming Language :: Python :: 3 :: Only
Classifier: Programming Language :: Python :: 3.10
Classifier: Programming Language :: Python :: 3.11
Classifier: Programming Language :: Python :: 3.12
Classifier: Programming Language :: Python :: 3.13
Classifier: Programming Language :: Python :: 3.14
Classifier: Programming Language :: Python :: Implementation :: CPython
Requires-Dist: django>4.2
Requires-Dist: fastmcp>=2.11.3
Requires-Dist: httpx>=0.28.1
Requires-Dist: platformdirs>=4.5.0
Requires-Dist: pydantic[email]>=2.11.7
Requires-Python: >=3.10
Project-URL: Documentation, https://github.com/joshuadavidthomas/mcp-django#README
Project-URL: Issues, https://github.com/joshuadavidthomas/mcp-django/issues
Project-URL: Source, https://github.com/joshuadavidthomas/mcp-django
